moon_cache/__init__.py
moon_cache/cache.py
moon_cache/context.py
moon_cache/request_wrapper.py
moon_cache-0.7.dist-info/LICENSE
moon_cache-0.7.dist-info/METADATA
moon_cache-0.7.dist-info/WHEEL
moon_cache-0.7.dist-info/top_level.txt
moon_cache-0.7.dist-info/RECORD
